mc_plugin_helper/__init__.py
mc_plugin_helper/__main__.py
mc_plugin_helper/cli.py
mc_plugin_helper/config.py
mc_plugin_helper/file_manager/__init__.py
mc_plugin_helper/file_manager/abstract.py
mc_plugin_helper/file_manager/factory.py
mc_plugin_helper/file_manager/local.py
mc_plugin_helper/plugin_manager.py
mc_plugin_helper/py.typed
mc_plugin_helper-0.1.0b0.dist-info/entry_points.txt
mc_plugin_helper-0.1.0b0.dist-info/LICENSE
mc_plugin_helper-0.1.0b0.dist-info/WHEEL
mc_plugin_helper-0.1.0b0.dist-info/METADATA
mc_plugin_helper-0.1.0b0.dist-info/RECORD
