Metadata-Version: 2.1
Name: mc-plugin-helper
Version: 0.1.0b0
Summary: Minecraft plugin helper, updates and checks versions of all plugins on a server!
Home-page: https://github.com/PerchunPak/mc-plugin-helper
License: MIT
Author: PerchunPak
Author-email: perchunpak@gmail.com
Requires-Python: >=3.7,<4.0
Classifier: Development Status :: 1 - Planning
Classifier: Intended Audience :: System Administrators
Classifier: License :: OSI Approved :: MIT License
Classifier: Natural Language :: English
Classifier: Operating System :: OS Independent
Classifier: Programming Language :: Python
Classifier: Programming Language :: Python :: 3
Classifier: Programming Language :: Python :: 3.10
Classifier: Programming Language :: Python :: 3.7
Classifier: Programming Language :: Python :: 3.8
Classifier: Programming Language :: Python :: 3.9
Classifier: Topic :: Home Automation
Classifier: Topic :: Internet
Classifier: Topic :: Internet :: File Transfer Protocol (FTP)
Classifier: Topic :: Software Development :: Version Control
Provides-Extra: docs
Requires-Dist: click (==8.0.4)
Requires-Dist: furo; extra == "docs"
Requires-Dist: m2r2 (>=0.3,<0.4); extra == "docs"
Requires-Dist: pyyaml (==6.0)
Requires-Dist: sphinx (>=4.5,<5.0); extra == "docs"
Requires-Dist: sphinx-autodoc-typehints (>=1.17,<2.0); extra == "docs"
Requires-Dist: sphinxcontrib-apidoc (>=0.3,<0.4); extra == "docs"
Requires-Dist: toml (>=0.10,<0.11); extra == "docs"
Requires-Dist: tomlkit (>=0.10,<0.11); extra == "docs"
Project-URL: Repository, https://github.com/PerchunPak/mc-plugin-helper
